main.py
jinafetch-0.3.1.dist-info/LICENSE.md
jinafetch-0.3.1.dist-info/METADATA
jinafetch-0.3.1.dist-info/WHEEL
jinafetch-0.3.1.dist-info/entry_points.txt
jinafetch-0.3.1.dist-info/top_level.txt
jinafetch-0.3.1.dist-info/RECORD
