Metadata-Version: 2.2
Name: jinafetch
Version: 0.3.1
Summary: CLI tool to fetch and save web content as Markdown files using Jina Reader API. Handles authentication and provides rich terminal output.
Project-URL: repository, https://github.com/engwerda/jinafetch
Project-URL: homepage, https://github.com/engwerda/jinafetch
Classifier: License :: OSI Approved :: MIT License
Requires-Python: >=3.12
License-File: LICENSE.md
Requires-Dist: appdirs<2.0,>=1.4.4
Requires-Dist: httpx>=0.28.1
Requires-Dist: python-dotenv>=1.0.1
Requires-Dist: rich>=13.9.4
Requires-Dist: typer>=0.15.1
